spacv/__init__.py
spacv/base_classes.py
spacv/grid_builder.py
spacv/spacv.py
spacv/utils.py
spacv/visualisation.py
spacv-0.0.22.dist-info/LICENSE
spacv-0.0.22.dist-info/METADATA
spacv-0.0.22.dist-info/WHEEL
spacv-0.0.22.dist-info/top_level.txt
spacv-0.0.22.dist-info/RECORD
