Metadata-Version: 2.1
Name: spacv
Version: 0.0.22
Summary: Spatial cross-validation in Python
Home-page: https://github.com/SamComber/spacv
Author: Sam Comber
Author-email: sam.comber@hotmail.co.uk
License: 3-Clause BSD
Platform: UNKNOWN
Classifier: License :: OSI Approved :: BSD License
Classifier: Programming Language :: Python :: 3
Classifier: Programming Language :: Python :: 3.5
Classifier: Programming Language :: Python :: 3.6
Classifier: Programming Language :: Python :: 3.7
Classifier: Programming Language :: Python :: 3 :: Only
Classifier: Programming Language :: Python :: Implementation :: CPython
Classifier: Framework :: Matplotlib
Requires-Python: >=3.6
Requires-Dist: numpy
Requires-Dist: matplotlib
Requires-Dist: pandas
Requires-Dist: geopandas
Requires-Dist: shapely
Requires-Dist: scikit-learn
Requires-Dist: scipy
Requires-Dist: pygeos
